tsv/__init__.py
tsv/cpu_features.pyi
tsv/cpu_features.pypy39-pp73-aarch64-linux-gnu.so
tsv/helper.py
tsv/parser.py
tsv/parser_plain.pypy39-pp73-aarch64-linux-gnu.so
tsv/py.typed
tsv2py-0.7.1.dist-info/LICENSE
tsv2py-0.7.1.dist-info/METADATA
tsv2py-0.7.1.dist-info/WHEEL
tsv2py-0.7.1.dist-info/top_level.txt
tsv2py-0.7.1.dist-info/zip-safe
tsv2py-0.7.1.dist-info/RECORD
