Metadata-Version: 2.1
Name: tsv2py
Version: 0.7.1
Summary: High-performance parser and generator for PostgreSQL-compatible tab-separated values (TSV)
Home-page: https://github.com/hunyadi/tsv2py
Author: Levente Hunyadi
Author-email: hunyadi@gmail.com
License: MIT
Classifier: Development Status :: 5 - Production/Stable
Classifier: Intended Audience :: Developers
Classifier: License :: OSI Approved :: MIT License
Classifier: Operating System :: MacOS
Classifier: Operating System :: Microsoft :: Windows
Classifier: Operating System :: POSIX :: Linux
Classifier: Programming Language :: C
Classifier: Programming Language :: Python :: 3
Classifier: Programming Language :: Python :: 3.8
Classifier: Programming Language :: Python :: 3.9
Classifier: Programming Language :: Python :: 3.10
Classifier: Programming Language :: Python :: 3.11
Classifier: Programming Language :: Python :: 3.12
Classifier: Programming Language :: Python :: Implementation :: CPython
Classifier: Topic :: File Formats
Classifier: Typing :: Typed
Requires-Python: >=3.8
License-File: LICENSE
